[
  {
    "name": "MATH 407",
    "type": "lecture",
    "location": "DMC 156",
    "start": "2025-01-13T11:00:00",
    "end": "2025-05-02T11:50:00",
    "links": [
      {
        "name": "Brightspace",
        "link": "https://brightspace.usc.edu/d2l/home/179981"
      }
    ]
  },
  {
    "name": "MATH 407",
    "type": "discussion",
    "location": "DMC 258",
    "start": "2025-01-13T12:00:00",
    "end": "2025-05-02T12:50:00",
    "links": [
      {
        "name": "Brightspace",
        "link": "https://brightspace.usc.edu/d2l/home/179981"
      }
    ]
  }
]
